arkitekt/__init__.py
arkitekt/apps/__init__.py
arkitekt/apps/easy.py
arkitekt/apps/fallbacks.py
arkitekt/apps/next.py
arkitekt/apps/qt.py
arkitekt/apps/service/__init__.py
arkitekt/apps/service/fakts.py
arkitekt/apps/service/fakts_next.py
arkitekt/apps/service/fakts_qt.py
arkitekt/apps/service/fluss.py
arkitekt/apps/service/grant_registry.py
arkitekt/apps/service/herre.py
arkitekt/apps/service/herre_qt.py
arkitekt/apps/service/kluster.py
arkitekt/apps/service/mikro.py
arkitekt/apps/service/mikro_next.py
arkitekt/apps/service/omero_ark.py
arkitekt/apps/service/rekuest.py
arkitekt/apps/service/rekuest_next.py
arkitekt/apps/service/unlok.py
arkitekt/apps/types.py
arkitekt/builders.py
arkitekt/cli/__init__.py
arkitekt/cli/commands/call/__init__.py
arkitekt/cli/commands/call/local.py
arkitekt/cli/commands/call/main.py
arkitekt/cli/commands/call/remote.py
arkitekt/cli/commands/gen/__init__.py
arkitekt/cli/commands/gen/compile.py
arkitekt/cli/commands/gen/init.py
arkitekt/cli/commands/gen/main.py
arkitekt/cli/commands/gen/watch.py
arkitekt/cli/commands/init/__init__.py
arkitekt/cli/commands/init/main.py
arkitekt/cli/commands/inspect/__init__.py
arkitekt/cli/commands/inspect/definitions.py
arkitekt/cli/commands/inspect/main.py
arkitekt/cli/commands/inspect/variables.py
arkitekt/cli/commands/manifest/__init__.py
arkitekt/cli/commands/manifest/inspect.py
arkitekt/cli/commands/manifest/main.py
arkitekt/cli/commands/manifest/scopes.py
arkitekt/cli/commands/manifest/version.py
arkitekt/cli/commands/manifest/wizard.py
arkitekt/cli/commands/port/__init__.py
arkitekt/cli/commands/port/build.py
arkitekt/cli/commands/port/init.py
arkitekt/cli/commands/port/main.py
arkitekt/cli/commands/port/publish.py
arkitekt/cli/commands/port/stage.py
arkitekt/cli/commands/port/utils.py
arkitekt/cli/commands/port/validate.py
arkitekt/cli/commands/port/wizard.py
arkitekt/cli/commands/run/__init__.py
arkitekt/cli/commands/run/dev.py
arkitekt/cli/commands/run/main.py
arkitekt/cli/commands/run/prod.py
arkitekt-0.7.7.dist-info/LICENSE
arkitekt-0.7.7.dist-info/METADATA
arkitekt-0.7.7.dist-info/WHEEL
arkitekt-0.7.7.dist-info/entry_points.txt
arkitekt-0.7.7.dist-info/RECORD
