Metadata-Version: 2.1
Name: arkitekt
Version: 0.7.7
Summary: client for the arkitekt platform
License: MIT
Author: jhnnsrs
Author-email: jhnnsrs@gmail.com
Requires-Python: >=3.8,<4.0
Classifier: License :: OSI Approved :: MIT License
Classifier: Programming Language :: Python :: 3
Classifier: Programming Language :: Python :: 3.8
Classifier: Programming Language :: Python :: 3.9
Classifier: Programming Language :: Python :: 3.10
Classifier: Programming Language :: Python :: 3.11
Provides-Extra: all
Provides-Extra: cli
Provides-Extra: extended
Provides-Extra: fluss
Provides-Extra: kluster
Provides-Extra: mikro
Provides-Extra: mikro-next
Provides-Extra: next
Provides-Extra: omero
Provides-Extra: reaktion
Provides-Extra: rekuest
Provides-Extra: unlok
Requires-Dist: dokker (>=0.1.21)
Requires-Dist: fakts (>=0.4.1)
Requires-Dist: fluss (>=0.1.61) ; extra == "fluss" or extra == "all" or extra == "extended"
Requires-Dist: herre (>=0.4.3)
Requires-Dist: kluster (>=0.0.3) ; (python_version >= "3.9" and python_version < "4.0") and (extra == "kluster" or extra == "extended")
Requires-Dist: koil (>=0.3.6)
Requires-Dist: mikro (>=0.3.95) ; extra == "mikro" or extra == "all" or extra == "extended"
Requires-Dist: mikro-next (>=0.1.6) ; (python_version >= "3.10" and python_version < "4.0") and (extra == "mikro-next" or extra == "next")
Requires-Dist: omero-ark (>=0.0.4) ; (python_version >= "3.8" and python_version < "4.0") and (extra == "omero" or extra == "extended")
Requires-Dist: reaktion (>=0.1.50) ; (python_version >= "3.8" and python_version < "4.0") and (extra == "reaktion" or extra == "all" or extra == "extended")
Requires-Dist: rekuest (>=0.2.29) ; extra == "cli" or extra == "rekuest" or extra == "all" or extra == "extended"
Requires-Dist: rich-click (>=1.6.1) ; extra == "cli" or extra == "all" or extra == "extended"
Requires-Dist: semver (>=3.0.1) ; extra == "cli" or extra == "all" or extra == "extended"
Requires-Dist: turms (>=0.5.0) ; (python_version >= "3.9" and python_version < "4.0") and (extra == "cli" or extra == "all" or extra == "extended")
Requires-Dist: unlok (>=0.1.19) ; extra == "unlok" or extra == "all" or extra == "extended"
Requires-Dist: watchfiles (>=0.18.1) ; extra == "cli" or extra == "all" or extra == "extended"
